bbox_objected-0.2.9.dist-info/METADATA
bbox_objected-0.2.9.dist-info/WHEEL
bbox_objected-0.2.9.dist-info/entry_points.txt
bbox_objected-0.2.9.dist-info/licenses/LICENSE
bbox_objected/__init__.py
bbox_objected/annotations.py
bbox_objected/bbox_utils.py
bbox_objected/sources/__init__.py
bbox_objected/sources/abs/__init__.py
bbox_objected/sources/abs/abs_bbox.py
bbox_objected/sources/abs/editor.py
bbox_objected/sources/bbox_creator.py
bbox_objected/sources/bbox_editor.py
bbox_objected/sources/bbox_getter.py
bbox_objected/sources/bbox_img.py
bbox_objected/sources/rel/__init__.py
bbox_objected/sources/rel/editor.py
bbox_objected/sources/rel/rel_bbox.py
bbox_objected-0.2.9.dist-info/RECORD
