Metadata-Version: 2.1
Name: bbox_objected
Version: 0.2.9
Summary: Manipulate bounding boxes as objects
Author-Email: SEBROVATER <sebrovskiy.k@gmail.com>
License: Apache-2.0
Project-URL: home, https://github.com/SEBROVATER/bbox_objected
Requires-Python: >=3.10
Provides-Extra: contrib
Requires-Dist: numpy>=1.22.0; extra == "contrib"
Requires-Dist: opencv-contrib-python>=4.7.0.71; extra == "contrib"
Provides-Extra: contrib-headless
Requires-Dist: numpy>=1.22.0; extra == "contrib-headless"
Requires-Dist: opencv-contrib-python-headless>=4.7.0.71; extra == "contrib-headless"
Provides-Extra: opencv
Requires-Dist: numpy>=1.22.0; extra == "opencv"
Requires-Dist: opencv-python>=4.7.0.71; extra == "opencv"
Provides-Extra: headless
Requires-Dist: numpy>=1.22.0; extra == "headless"
Requires-Dist: opencv-python-headless>=4.7.0.71; extra == "headless"
